semversioner/__init__.py
semversioner/__main__.py
semversioner/__version__.py
semversioner/cli.py
semversioner/core.py
semversioner/models.py
semversioner/storage.py
tests/resources/__init__.py
semversioner-2.0.8.dist-info/LICENSE
semversioner-2.0.8.dist-info/METADATA
semversioner-2.0.8.dist-info/WHEEL
semversioner-2.0.8.dist-info/entry_points.txt
semversioner-2.0.8.dist-info/top_level.txt
semversioner-2.0.8.dist-info/RECORD
