Metadata-Version: 2.1
Name: semversioner
Version: 2.0.8
Summary: Manage properly semver in your repository
Home-page: https://github.com/raulgomis/semversioner
Author: Raul Gomis
Author-email: raulgomis@gmail.com
License: MIT
Platform: UNKNOWN
Classifier: Development Status :: 5 - Production/Stable
Classifier: Environment :: Console
Classifier: Intended Audience :: Developers
Classifier: Intended Audience :: End Users/Desktop
Classifier: License :: OSI Approved :: MIT License
Classifier: Programming Language :: Python
Classifier: Programming Language :: Python :: 3
Classifier: Programming Language :: Python :: 3.8
Classifier: Programming Language :: Python :: 3.9
Classifier: Programming Language :: Python :: 3.10
Classifier: Programming Language :: Python :: 3.11
Classifier: Programming Language :: Python :: 3.12
Classifier: Operating System :: OS Independent
Requires-Python: >=3.8.0
Requires-Dist: click>=8.0.0
Requires-Dist: jinja2>=3.0.0
Requires-Dist: packaging>=21.0
